mtanvil/__init__.py
mtanvil-0.3.1.dist-info/METADATA
mtanvil-0.3.1.dist-info/WHEEL
mtanvil-0.3.1.dist-info/licenses/LICENSE
mtanvil-0.3.1.dist-info/RECORD
