Metadata-Version: 2.4
Name: mtanvil
Version: 0.3.1
Summary: Parser and editor for Luanti worlds
Project-URL: Homepage, https://github.com/fancyfinn9/mtanvil
Project-URL: Issues, https://github.com/fancyfinn9/mtanvil/issues
Project-URL: Docs, https://github.com/fancyfinn9/mtanvil/wiki
Author-email: fancyfinn9 <fancyfinn9@proton.me>
License-Expression: GPL-3.0-only
License-File: LICENSE
Keywords: Luanti,Minetest
Classifier: Development Status :: 3 - Alpha
Classifier: License :: OSI Approved :: GNU General Public License v3 (GPLv3)
Classifier: Operating System :: OS Independent
Classifier: Programming Language :: Python :: 3
Classifier: Topic :: File Formats
Requires-Python: >=3.9
Requires-Dist: zstandard
